greennode/__init__.py
greennode/abstract/__init__.py
greennode/abstract/api_requestor.py
greennode/cli/__init__.py
greennode/cli/cli.py
greennode/client.py
greennode/constants.py
greennode/error.py
greennode/greennode_response.py
greennode/resources/__init__.py
greennode/resources/authen.py
greennode/resources/chat_completions.py
greennode/resources/completions.py
greennode/resources/embeddings.py
greennode/resources/image_gen.py
greennode/resources/list_models.py
greennode/resources/reranks.py
greennode/resources/speech.py
greennode/resources/transcriptions.py
greennode/types/__init__.py
greennode/types/abstract.py
greennode/types/authen.py
greennode/types/chat_completions.py
greennode/types/common.py
greennode/types/completions.py
greennode/types/embeddings.py
greennode/types/error.py
greennode/types/image_gen.py
greennode/types/list_models.py
greennode/types/reranks.py
greennode/types/speech.py
greennode/types/transcriptions.py
greennode/utils/__init__.py
greennode/utils/_log.py
greennode/utils/api_helpers.py
greennode/utils/tools.py
greennode/version.py
greennode-0.0.3.dist-info/LICENSE
greennode-0.0.3.dist-info/METADATA
greennode-0.0.3.dist-info/WHEEL
greennode-0.0.3.dist-info/entry_points.txt
greennode-0.0.3.dist-info/RECORD
