Metadata-Version: 2.3
Name: greennode
Version: 0.0.3
Summary: Python client for GreenNode's Cloud Platform!
License: Apache-2.0
Author: GreenNode AI
Author-email: support@greennode.ai
Requires-Python: >=3.9,<4.0
Classifier: License :: OSI Approved :: Apache Software License
Classifier: Operating System :: POSIX :: Linux
Classifier: Programming Language :: Python :: 3
Classifier: Programming Language :: Python :: 3.9
Classifier: Programming Language :: Python :: 3.10
Classifier: Programming Language :: Python :: 3.11
Classifier: Programming Language :: Python :: 3.12
Classifier: Programming Language :: Python :: 3.13
Requires-Dist: datasets (>=3.0.0)
Requires-Dist: pydantic (>=2.11.7,<3.0.0)
Requires-Dist: pytest (>=8.4.0,<9.0.0)
Requires-Dist: tabulate (>=0.9.0,<0.10.0)
Project-URL: Bug Tracker, https://github.com/greennode-ai/greennode-python/issues
Project-URL: Homepage, https://github.com/greennode-ai/greennode-python
Project-URL: Repository, https://github.com/greennode-ai/greennode-python
